tengine/__init__.py
tengine_examples/casino.py
tengine_examples/flappy.py
tengine_examples/snake.py
t_engine-0.0.3.dist-info/METADATA
t_engine-0.0.3.dist-info/WHEEL
t_engine-0.0.3.dist-info/licenses/LICENSE
t_engine-0.0.3.dist-info/RECORD
