Metadata-Version: 2.1
Name: t-engine
Version: 0.0.3
Summary: A terminal engine to create text based games!
Project-URL: Homepage, https://github.com/iinsertNameHere
Project-URL: Issues, https://github.com/iinsertNameHere/issues
Author: iinsert
License-File: LICENSE
Classifier: License :: OSI Approved :: MIT License
Classifier: Operating System :: OS Independent
Classifier: Programming Language :: Python :: 3
Requires-Python: >=3.11
